kwave/__init__.py
kwave/data.py
kwave/enums.py
kwave/executor.py
kwave/kWaveSimulation.py
kwave/kgrid.py
kwave/kmedium.py
kwave/ksensor.py
kwave/ksource.py
kwave/kspaceFirstOrder2D.py
kwave/kspaceFirstOrder3D.py
kwave/kspaceFirstOrderAS.py
kwave/kspaceLineRecon.py
kwave/kspacePlaneRecon.py
kwave/ktransducer.py
kwave/recorder.py
kwave/kWaveSimulation_helper/__init__.py
kwave/kWaveSimulation_helper/create_absorption_variables.py
kwave/kWaveSimulation_helper/display_simulation_params.py
kwave/kWaveSimulation_helper/expand_grid_matrices.py
kwave/kWaveSimulation_helper/retract_transducer_grid_size.py
kwave/kWaveSimulation_helper/save_to_disk_func.py
kwave/kWaveSimulation_helper/scale_source_terms_func.py
kwave/kWaveSimulation_helper/set_sound_speed_ref.py
kwave/options/__init__.py
kwave/options/simulation_execution_options.py
kwave/options/simulation_options.py
kwave/reconstruction/__init__.py
kwave/reconstruction/beamform.py
kwave/reconstruction/tools.py
kwave/utils/__init__.py
kwave/utils/angular_spectrum.py
kwave/utils/angular_spectrum_cw.py
kwave/utils/atten_comp.py
kwave/utils/checks.py
kwave/utils/colormap.py
kwave/utils/conversion.py
kwave/utils/data.py
kwave/utils/dotdictionary.py
kwave/utils/filters.py
kwave/utils/interp.py
kwave/utils/io.py
kwave/utils/kwave_array.py
kwave/utils/mapgen.py
kwave/utils/math.py
kwave/utils/matlab.py
kwave/utils/matrix.py
kwave/utils/plot.py
kwave/utils/pml.py
kwave/utils/signals.py
kwave/utils/tictoc.py
kwave/utils/typing.py
k_wave_python-0.4.0.dist-info/METADATA
k_wave_python-0.4.0.dist-info/WHEEL
k_wave_python-0.4.0.dist-info/licenses/LICENSE
k_wave_python-0.4.0.dist-info/RECORD
