Metadata-Version: 2.3
Name: k-Wave-python
Version: 0.4.0
Summary: Acoustics toolbox for time domain acoustic and ultrasound simulations in complex and tissue-realistic media.
Project-URL: Homepage, http://www.k-wave.org/
Project-URL: Documentation, https://waltersimson.com/k-wave-python/
Project-URL: Repository, https://github.com/waltsims/k-wave-python
Project-URL: Bug-tracker, https://github.com/waltsims/k-wave-python/issues
Author-email: Farid Yagubbayli <farid.yagubbayli@tum.de>, Walter Simson <walter.simson@tum.de>
Maintainer-email: Walter Simson <walter.simson@tum.de>, Farid Yagubbayli <farid.yagubbayli@tum.de>, David Sinden <david.sinden@mevis.fraunhofer.de>
License:                    GNU LESSER GENERAL PUBLIC LICENSE
Classifier: License :: OSI Approved :: GNU General Public License v3 (GPLv3)
Classifier: Operating System :: OS Independent
Classifier: Programming Language :: Python :: 3
Requires-Python: >=3.10
Requires-Dist: beartype==0.19.0
Requires-Dist: deepdiff==8.1.1
Requires-Dist: h5py==3.12.1
Requires-Dist: jaxtyping==0.2.36
Requires-Dist: matplotlib==3.10.0
Requires-Dist: numpy<2.3.0,>=1.22.2
Requires-Dist: opencv-python==4.10.0.84
Requires-Dist: scipy==1.14.1
Provides-Extra: dev
Requires-Dist: pre-commit==4.0.1; extra == 'dev'
Provides-Extra: docs
Requires-Dist: furo==2024.8.6; extra == 'docs'
Requires-Dist: sphinx-copybutton==0.5.2; extra == 'docs'
Requires-Dist: sphinx-mdinclude==0.6.2; extra == 'docs'
Requires-Dist: sphinx-tabs==3.4.7; extra == 'docs'
Requires-Dist: sphinx-toolbox==3.8.0; extra == 'docs'
Provides-Extra: example
Requires-Dist: gdown==5.2.0; extra == 'example'
Provides-Extra: test
Requires-Dist: coverage==7.6.9; extra == 'test'
Requires-Dist: phantominator; extra == 'test'
Requires-Dist: pytest; extra == 'test'
Requires-Dist: requests==2.32.3; extra == 'test'
Requires-Dist: testfixtures==8.3.0; extra == 'test'
